{
  "depotid": "1012113",
  "updated_at": "2026-05-15T15:15:51Z",
  "manifests": [
    {
      "depotid": "1012113",
      "manifestid": "1109077183623693183",
      "source_repo": "qwe213312/k25FCdfEOoEJ42S6",
      "source_type": "github_tree_index",
      "status": "unverified",
      "confidence_score": 25
    },
    {
      "depotid": "1012113",
      "manifestid": "1618737427987170674",
      "source_repo": "qwe213312/k25FCdfEOoEJ42S6",
      "source_type": "github_tree_index",
      "status": "unverified",
      "confidence_score": 25
    },
    {
      "depotid": "1012113",
      "manifestid": "1708364373259188338",
      "source_repo": "qwe213312/k25FCdfEOoEJ42S6",
      "source_type": "github_tree_index",
      "status": "unverified",
      "confidence_score": 25
    },
    {
      "depotid": "1012113",
      "manifestid": "194787345282542374",
      "source_repo": "qwe213312/k25FCdfEOoEJ42S6",
      "source_type": "github_tree_index",
      "status": "unverified",
      "confidence_score": 25
    },
    {
      "depotid": "1012113",
      "manifestid": "2252864225846670121",
      "source_repo": "qwe213312/k25FCdfEOoEJ42S6",
      "source_type": "github_tree_index",
      "status": "unverified",
      "confidence_score": 25
    },
    {
      "depotid": "1012113",
      "manifestid": "227762343004892065",
      "source_repo": "qwe213312/k25FCdfEOoEJ42S6",
      "source_type": "github_tree_index",
      "status": "unverified",
      "confidence_score": 25
    },
    {
      "depotid": "1012113",
      "manifestid": "244089004163705885",
      "source_repo": "qwe213312/k25FCdfEOoEJ42S6",
      "source_type": "github_tree_index",
      "status": "unverified",
      "confidence_score": 25
    },
    {
      "depotid": "1012113",
      "manifestid": "2609283907565414382",
      "source_repo": "qwe213312/k25FCdfEOoEJ42S6",
      "source_type": "github_tree_index",
      "status": "unverified",
      "confidence_score": 25
    },
    {
      "depotid": "1012113",
      "manifestid": "2848590689466677564",
      "source_repo": "qwe213312/k25FCdfEOoEJ42S6",
      "source_type": "github_tree_index",
      "status": "unverified",
      "confidence_score": 25
    },
    {
      "depotid": "1012113",
      "manifestid": "2954317416605580997",
      "source_repo": "qwe213312/k25FCdfEOoEJ42S6",
      "source_type": "github_tree_index",
      "status": "unverified",
      "confidence_score": 25
    },
    {
      "depotid": "1012113",
      "manifestid": "3085328447040431923",
      "source_repo": "qwe213312/k25FCdfEOoEJ42S6",
      "source_type": "github_tree_index",
      "status": "unverified",
      "confidence_score": 25
    },
    {
      "depotid": "1012113",
      "manifestid": "3426362081693219410",
      "source_repo": "qwe213312/k25FCdfEOoEJ42S6",
      "source_type": "github_tree_index",
      "status": "unverified",
      "confidence_score": 25
    },
    {
      "depotid": "1012113",
      "manifestid": "3436105926133759236",
      "source_repo": "qwe213312/k25FCdfEOoEJ42S6",
      "source_type": "github_tree_index",
      "status": "unverified",
      "confidence_score": 25
    },
    {
      "depotid": "1012113",
      "manifestid": "3840105179418882613",
      "source_repo": "qwe213312/k25FCdfEOoEJ42S6",
      "source_type": "github_tree_index",
      "status": "unverified",
      "confidence_score": 25
    },
    {
      "depotid": "1012113",
      "manifestid": "4221447515323805964",
      "source_repo": "qwe213312/k25FCdfEOoEJ42S6",
      "source_type": "github_tree_index",
      "status": "unverified",
      "confidence_score": 25
    },
    {
      "depotid": "1012113",
      "manifestid": "4538560631192349368",
      "source_repo": "qwe213312/k25FCdfEOoEJ42S6",
      "source_type": "github_tree_index",
      "status": "unverified",
      "confidence_score": 25
    },
    {
      "depotid": "1012113",
      "manifestid": "461762862975554192",
      "source_repo": "qwe213312/k25FCdfEOoEJ42S6",
      "source_type": "github_tree_index",
      "status": "unverified",
      "confidence_score": 25
    },
    {
      "depotid": "1012113",
      "manifestid": "4778704679688580231",
      "source_repo": "qwe213312/k25FCdfEOoEJ42S6",
      "source_type": "github_tree_index",
      "status": "unverified",
      "confidence_score": 25
    },
    {
      "depotid": "1012113",
      "manifestid": "5272927471369312311",
      "source_repo": "qwe213312/k25FCdfEOoEJ42S6",
      "source_type": "github_tree_index",
      "status": "unverified",
      "confidence_score": 25
    },
    {
      "depotid": "1012113",
      "manifestid": "5490835534070902975",
      "source_repo": "qwe213312/k25FCdfEOoEJ42S6",
      "source_type": "github_tree_index",
      "status": "unverified",
      "confidence_score": 25
    },
    {
      "depotid": "1012113",
      "manifestid": "5568055767330070438",
      "source_repo": "qwe213312/k25FCdfEOoEJ42S6",
      "source_type": "github_tree_index",
      "status": "unverified",
      "confidence_score": 25
    },
    {
      "depotid": "1012113",
      "manifestid": "5885667491725423736",
      "source_repo": "qwe213312/k25FCdfEOoEJ42S6",
      "source_type": "github_tree_index",
      "status": "unverified",
      "confidence_score": 25
    },
    {
      "depotid": "1012113",
      "manifestid": "5937822336566652806",
      "source_repo": "qwe213312/k25FCdfEOoEJ42S6",
      "source_type": "github_tree_index",
      "status": "unverified",
      "confidence_score": 25
    },
    {
      "depotid": "1012113",
      "manifestid": "6273222672261030793",
      "source_repo": "qwe213312/k25FCdfEOoEJ42S6",
      "source_type": "github_tree_index",
      "status": "unverified",
      "confidence_score": 25
    },
    {
      "depotid": "1012113",
      "manifestid": "6311947195755285394",
      "source_repo": "qwe213312/k25FCdfEOoEJ42S6",
      "source_type": "github_tree_index",
      "status": "unverified",
      "confidence_score": 25
    },
    {
      "depotid": "1012113",
      "manifestid": "6640884947845763103",
      "source_repo": "qwe213312/k25FCdfEOoEJ42S6",
      "source_type": "github_tree_index",
      "status": "unverified",
      "confidence_score": 25
    },
    {
      "depotid": "1012113",
      "manifestid": "6734715492430110811",
      "source_repo": "qwe213312/k25FCdfEOoEJ42S6",
      "source_type": "github_tree_index",
      "status": "unverified",
      "confidence_score": 25
    },
    {
      "depotid": "1012113",
      "manifestid": "6740852221520206145",
      "source_repo": "qwe213312/k25FCdfEOoEJ42S6",
      "source_type": "github_tree_index",
      "status": "unverified",
      "confidence_score": 25
    },
    {
      "depotid": "1012113",
      "manifestid": "6784792427619758868",
      "source_repo": "qwe213312/k25FCdfEOoEJ42S6",
      "source_type": "github_tree_index",
      "status": "unverified",
      "confidence_score": 25
    },
    {
      "depotid": "1012113",
      "manifestid": "7027254155870392321",
      "source_repo": "qwe213312/k25FCdfEOoEJ42S6",
      "source_type": "github_tree_index",
      "status": "unverified",
      "confidence_score": 25
    },
    {
      "depotid": "1012113",
      "manifestid": "7057957511113202137",
      "source_repo": "qwe213312/k25FCdfEOoEJ42S6",
      "source_type": "github_tree_index",
      "status": "unverified",
      "confidence_score": 25
    },
    {
      "depotid": "1012113",
      "manifestid": "7290767476669264273",
      "source_repo": "qwe213312/k25FCdfEOoEJ42S6",
      "source_type": "github_tree_index",
      "status": "unverified",
      "confidence_score": 25
    },
    {
      "depotid": "1012113",
      "manifestid": "7828126082183770385",
      "source_repo": "qwe213312/k25FCdfEOoEJ42S6",
      "source_type": "github_tree_index",
      "status": "unverified",
      "confidence_score": 25
    },
    {
      "depotid": "1012113",
      "manifestid": "8497984560039816147",
      "source_repo": "qwe213312/k25FCdfEOoEJ42S6",
      "source_type": "github_tree_index",
      "status": "unverified",
      "confidence_score": 25
    },
    {
      "depotid": "1012113",
      "manifestid": "870607491001258325",
      "source_repo": "qwe213312/k25FCdfEOoEJ42S6",
      "source_type": "github_tree_index",
      "status": "unverified",
      "confidence_score": 25
    }
  ]
}
