{
  "depotid": "1786832",
  "updated_at": "2026-05-20T06:50:32Z",
  "manifests": [
    {
      "depotid": "1786832",
      "manifestid": "2250836498485682014",
      "source_repo": "qwe213312/k25FCdfEOoEJ42S6",
      "source_type": "github_tree_index",
      "status": "unverified",
      "confidence_score": 25
    },
    {
      "depotid": "1786832",
      "manifestid": "2449704400235353887",
      "source_repo": "qwe213312/k25FCdfEOoEJ42S6",
      "source_type": "github_tree_index",
      "status": "unverified",
      "confidence_score": 25
    },
    {
      "depotid": "1786832",
      "manifestid": "6361417748997037664",
      "source_repo": "qwe213312/k25FCdfEOoEJ42S6",
      "source_type": "github_tree_index",
      "status": "unverified",
      "confidence_score": 25
    }
  ]
}
