{
  "depotid": "1900252",
  "updated_at": "2026-05-15T13:30:09Z",
  "manifests": [
    {
      "depotid": "1900252",
      "manifestid": "1026246628286458447",
      "source_repo": "qwe213312/k25FCdfEOoEJ42S6",
      "source_type": "github_tree_index",
      "status": "unverified",
      "confidence_score": 25
    },
    {
      "depotid": "1900252",
      "manifestid": "3502818791390625699",
      "source_repo": "qwe213312/k25FCdfEOoEJ42S6",
      "source_type": "github_tree_index",
      "status": "unverified",
      "confidence_score": 25
    },
    {
      "depotid": "1900252",
      "manifestid": "6579606093045670923",
      "source_repo": "qwe213312/k25FCdfEOoEJ42S6",
      "source_type": "github_tree_index",
      "status": "unverified",
      "confidence_score": 25
    },
    {
      "depotid": "1900252",
      "manifestid": "6625687100524901004",
      "source_repo": "qwe213312/k25FCdfEOoEJ42S6",
      "source_type": "github_tree_index",
      "status": "unverified",
      "confidence_score": 25
    },
    {
      "depotid": "1900252",
      "manifestid": "8563416854065579085",
      "source_repo": "qwe213312/k25FCdfEOoEJ42S6",
      "source_type": "github_tree_index",
      "status": "unverified",
      "confidence_score": 25
    },
    {
      "depotid": "1900252",
      "manifestid": "8757880414020495615",
      "source_repo": "qwe213312/k25FCdfEOoEJ42S6",
      "source_type": "github_tree_index",
      "status": "unverified",
      "confidence_score": 25
    }
  ]
}
