{
  "depotid": "1962666",
  "updated_at": "2026-05-15T15:15:51Z",
  "manifests": [
    {
      "depotid": "1962666",
      "manifestid": "1020938993693330878",
      "source_repo": "qwe213312/k25FCdfEOoEJ42S6",
      "source_type": "github_tree_index",
      "status": "unverified",
      "confidence_score": 25
    },
    {
      "depotid": "1962666",
      "manifestid": "1102739823969456110",
      "source_repo": "qwe213312/k25FCdfEOoEJ42S6",
      "source_type": "github_tree_index",
      "status": "unverified",
      "confidence_score": 25
    },
    {
      "depotid": "1962666",
      "manifestid": "1347780560018098615",
      "source_repo": "qwe213312/k25FCdfEOoEJ42S6",
      "source_type": "github_tree_index",
      "status": "unverified",
      "confidence_score": 25
    },
    {
      "depotid": "1962666",
      "manifestid": "1371723623082247902",
      "source_repo": "qwe213312/k25FCdfEOoEJ42S6",
      "source_type": "github_tree_index",
      "status": "unverified",
      "confidence_score": 25
    },
    {
      "depotid": "1962666",
      "manifestid": "1545386552242710627",
      "source_repo": "qwe213312/k25FCdfEOoEJ42S6",
      "source_type": "github_tree_index",
      "status": "unverified",
      "confidence_score": 25
    },
    {
      "depotid": "1962666",
      "manifestid": "1597384552903860352",
      "source_repo": "qwe213312/k25FCdfEOoEJ42S6",
      "source_type": "github_tree_index",
      "status": "unverified",
      "confidence_score": 25
    },
    {
      "depotid": "1962666",
      "manifestid": "1651984465175628463",
      "source_repo": "qwe213312/k25FCdfEOoEJ42S6",
      "source_type": "github_tree_index",
      "status": "unverified",
      "confidence_score": 25
    },
    {
      "depotid": "1962666",
      "manifestid": "1889199089354981552",
      "source_repo": "qwe213312/k25FCdfEOoEJ42S6",
      "source_type": "github_tree_index",
      "status": "unverified",
      "confidence_score": 25
    },
    {
      "depotid": "1962666",
      "manifestid": "1987084070158726245",
      "source_repo": "qwe213312/k25FCdfEOoEJ42S6",
      "source_type": "github_tree_index",
      "status": "unverified",
      "confidence_score": 25
    },
    {
      "depotid": "1962666",
      "manifestid": "2331158033238068995",
      "source_repo": "qwe213312/k25FCdfEOoEJ42S6",
      "source_type": "github_tree_index",
      "status": "unverified",
      "confidence_score": 25
    },
    {
      "depotid": "1962666",
      "manifestid": "2508092112824235646",
      "source_repo": "qwe213312/k25FCdfEOoEJ42S6",
      "source_type": "github_tree_index",
      "status": "unverified",
      "confidence_score": 25
    },
    {
      "depotid": "1962666",
      "manifestid": "2705544932914805953",
      "source_repo": "qwe213312/k25FCdfEOoEJ42S6",
      "source_type": "github_tree_index",
      "status": "unverified",
      "confidence_score": 25
    },
    {
      "depotid": "1962666",
      "manifestid": "2758228047141361482",
      "source_repo": "qwe213312/k25FCdfEOoEJ42S6",
      "source_type": "github_tree_index",
      "status": "unverified",
      "confidence_score": 25
    },
    {
      "depotid": "1962666",
      "manifestid": "2796885721632313059",
      "source_repo": "qwe213312/k25FCdfEOoEJ42S6",
      "source_type": "github_tree_index",
      "status": "unverified",
      "confidence_score": 25
    },
    {
      "depotid": "1962666",
      "manifestid": "303513774002641044",
      "source_repo": "qwe213312/k25FCdfEOoEJ42S6",
      "source_type": "github_tree_index",
      "status": "unverified",
      "confidence_score": 25
    },
    {
      "depotid": "1962666",
      "manifestid": "3074797085476319141",
      "source_repo": "qwe213312/k25FCdfEOoEJ42S6",
      "source_type": "github_tree_index",
      "status": "unverified",
      "confidence_score": 25
    },
    {
      "depotid": "1962666",
      "manifestid": "3210366599346663599",
      "source_repo": "qwe213312/k25FCdfEOoEJ42S6",
      "source_type": "github_tree_index",
      "status": "unverified",
      "confidence_score": 25
    },
    {
      "depotid": "1962666",
      "manifestid": "335996632118035896",
      "source_repo": "qwe213312/k25FCdfEOoEJ42S6",
      "source_type": "github_tree_index",
      "status": "unverified",
      "confidence_score": 25
    },
    {
      "depotid": "1962666",
      "manifestid": "3445814735678730995",
      "source_repo": "qwe213312/k25FCdfEOoEJ42S6",
      "source_type": "github_tree_index",
      "status": "unverified",
      "confidence_score": 25
    },
    {
      "depotid": "1962666",
      "manifestid": "3674110882459213150",
      "source_repo": "qwe213312/k25FCdfEOoEJ42S6",
      "source_type": "github_tree_index",
      "status": "unverified",
      "confidence_score": 25
    },
    {
      "depotid": "1962666",
      "manifestid": "3702811789918009542",
      "source_repo": "qwe213312/k25FCdfEOoEJ42S6",
      "source_type": "github_tree_index",
      "status": "unverified",
      "confidence_score": 25
    },
    {
      "depotid": "1962666",
      "manifestid": "4036355908799745963",
      "source_repo": "qwe213312/k25FCdfEOoEJ42S6",
      "source_type": "github_tree_index",
      "status": "unverified",
      "confidence_score": 25
    },
    {
      "depotid": "1962666",
      "manifestid": "4136286988662945057",
      "source_repo": "qwe213312/k25FCdfEOoEJ42S6",
      "source_type": "github_tree_index",
      "status": "unverified",
      "confidence_score": 25
    },
    {
      "depotid": "1962666",
      "manifestid": "4270241464081855686",
      "source_repo": "qwe213312/k25FCdfEOoEJ42S6",
      "source_type": "github_tree_index",
      "status": "unverified",
      "confidence_score": 25
    },
    {
      "depotid": "1962666",
      "manifestid": "4301348532745536310",
      "source_repo": "qwe213312/k25FCdfEOoEJ42S6",
      "source_type": "github_tree_index",
      "status": "unverified",
      "confidence_score": 25
    },
    {
      "depotid": "1962666",
      "manifestid": "4463900553074939252",
      "source_repo": "qwe213312/k25FCdfEOoEJ42S6",
      "source_type": "github_tree_index",
      "status": "unverified",
      "confidence_score": 25
    },
    {
      "depotid": "1962666",
      "manifestid": "4634518935280745530",
      "source_repo": "qwe213312/k25FCdfEOoEJ42S6",
      "source_type": "github_tree_index",
      "status": "unverified",
      "confidence_score": 25
    },
    {
      "depotid": "1962666",
      "manifestid": "4772370252255325058",
      "source_repo": "qwe213312/k25FCdfEOoEJ42S6",
      "source_type": "github_tree_index",
      "status": "unverified",
      "confidence_score": 25
    },
    {
      "depotid": "1962666",
      "manifestid": "4780886634251084702",
      "source_repo": "qwe213312/k25FCdfEOoEJ42S6",
      "source_type": "github_tree_index",
      "status": "unverified",
      "confidence_score": 25
    },
    {
      "depotid": "1962666",
      "manifestid": "501981803389033214",
      "source_repo": "qwe213312/k25FCdfEOoEJ42S6",
      "source_type": "github_tree_index",
      "status": "unverified",
      "confidence_score": 25
    },
    {
      "depotid": "1962666",
      "manifestid": "5079688647541089757",
      "source_repo": "qwe213312/k25FCdfEOoEJ42S6",
      "source_type": "github_tree_index",
      "status": "unverified",
      "confidence_score": 25
    },
    {
      "depotid": "1962666",
      "manifestid": "5276562104387015192",
      "source_repo": "qwe213312/k25FCdfEOoEJ42S6",
      "source_type": "github_tree_index",
      "status": "unverified",
      "confidence_score": 25
    },
    {
      "depotid": "1962666",
      "manifestid": "52933404555323977",
      "source_repo": "qwe213312/k25FCdfEOoEJ42S6",
      "source_type": "github_tree_index",
      "status": "unverified",
      "confidence_score": 25
    },
    {
      "depotid": "1962666",
      "manifestid": "5452362976291306512",
      "source_repo": "qwe213312/k25FCdfEOoEJ42S6",
      "source_type": "github_tree_index",
      "status": "unverified",
      "confidence_score": 25
    },
    {
      "depotid": "1962666",
      "manifestid": "571140795570358706",
      "source_repo": "qwe213312/k25FCdfEOoEJ42S6",
      "source_type": "github_tree_index",
      "status": "unverified",
      "confidence_score": 25
    },
    {
      "depotid": "1962666",
      "manifestid": "5739282861034130822",
      "source_repo": "qwe213312/k25FCdfEOoEJ42S6",
      "source_type": "github_tree_index",
      "status": "unverified",
      "confidence_score": 25
    },
    {
      "depotid": "1962666",
      "manifestid": "5926047578410005198",
      "source_repo": "qwe213312/k25FCdfEOoEJ42S6",
      "source_type": "github_tree_index",
      "status": "unverified",
      "confidence_score": 25
    },
    {
      "depotid": "1962666",
      "manifestid": "6022367412577027394",
      "source_repo": "qwe213312/k25FCdfEOoEJ42S6",
      "source_type": "github_tree_index",
      "status": "unverified",
      "confidence_score": 25
    },
    {
      "depotid": "1962666",
      "manifestid": "6272737831208447922",
      "source_repo": "qwe213312/k25FCdfEOoEJ42S6",
      "source_type": "github_tree_index",
      "status": "unverified",
      "confidence_score": 25
    },
    {
      "depotid": "1962666",
      "manifestid": "6277153069994922493",
      "source_repo": "qwe213312/k25FCdfEOoEJ42S6",
      "source_type": "github_tree_index",
      "status": "unverified",
      "confidence_score": 25
    },
    {
      "depotid": "1962666",
      "manifestid": "6329166156751606490",
      "source_repo": "qwe213312/k25FCdfEOoEJ42S6",
      "source_type": "github_tree_index",
      "status": "unverified",
      "confidence_score": 25
    },
    {
      "depotid": "1962666",
      "manifestid": "6359697316480294524",
      "source_repo": "qwe213312/k25FCdfEOoEJ42S6",
      "source_type": "github_tree_index",
      "status": "unverified",
      "confidence_score": 25
    },
    {
      "depotid": "1962666",
      "manifestid": "6397034856716907111",
      "source_repo": "qwe213312/k25FCdfEOoEJ42S6",
      "source_type": "github_tree_index",
      "status": "unverified",
      "confidence_score": 25
    },
    {
      "depotid": "1962666",
      "manifestid": "6397463960118396137",
      "source_repo": "qwe213312/k25FCdfEOoEJ42S6",
      "source_type": "github_tree_index",
      "status": "unverified",
      "confidence_score": 25
    },
    {
      "depotid": "1962666",
      "manifestid": "6644677541051059398",
      "source_repo": "qwe213312/k25FCdfEOoEJ42S6",
      "source_type": "github_tree_index",
      "status": "unverified",
      "confidence_score": 25
    },
    {
      "depotid": "1962666",
      "manifestid": "7096023817396921249",
      "source_repo": "qwe213312/k25FCdfEOoEJ42S6",
      "source_type": "github_tree_index",
      "status": "unverified",
      "confidence_score": 25
    },
    {
      "depotid": "1962666",
      "manifestid": "7135065292956307803",
      "source_repo": "qwe213312/k25FCdfEOoEJ42S6",
      "source_type": "github_tree_index",
      "status": "unverified",
      "confidence_score": 25
    },
    {
      "depotid": "1962666",
      "manifestid": "7248324912346397537",
      "source_repo": "qwe213312/k25FCdfEOoEJ42S6",
      "source_type": "github_tree_index",
      "status": "unverified",
      "confidence_score": 25
    },
    {
      "depotid": "1962666",
      "manifestid": "7338820067484531424",
      "source_repo": "qwe213312/k25FCdfEOoEJ42S6",
      "source_type": "github_tree_index",
      "status": "unverified",
      "confidence_score": 25
    },
    {
      "depotid": "1962666",
      "manifestid": "7474767709608244469",
      "source_repo": "qwe213312/k25FCdfEOoEJ42S6",
      "source_type": "github_tree_index",
      "status": "unverified",
      "confidence_score": 25
    },
    {
      "depotid": "1962666",
      "manifestid": "7585285219615398141",
      "source_repo": "qwe213312/k25FCdfEOoEJ42S6",
      "source_type": "github_tree_index",
      "status": "unverified",
      "confidence_score": 25
    },
    {
      "depotid": "1962666",
      "manifestid": "8074930431920854560",
      "source_repo": "qwe213312/k25FCdfEOoEJ42S6",
      "source_type": "github_tree_index",
      "status": "unverified",
      "confidence_score": 25
    },
    {
      "depotid": "1962666",
      "manifestid": "8340809549180475203",
      "source_repo": "qwe213312/k25FCdfEOoEJ42S6",
      "source_type": "github_tree_index",
      "status": "unverified",
      "confidence_score": 25
    },
    {
      "depotid": "1962666",
      "manifestid": "8391806692494313028",
      "source_repo": "qwe213312/k25FCdfEOoEJ42S6",
      "source_type": "github_tree_index",
      "status": "unverified",
      "confidence_score": 25
    },
    {
      "depotid": "1962666",
      "manifestid": "8477430869016347581",
      "source_repo": "qwe213312/k25FCdfEOoEJ42S6",
      "source_type": "github_tree_index",
      "status": "unverified",
      "confidence_score": 25
    },
    {
      "depotid": "1962666",
      "manifestid": "8907949679112418979",
      "source_repo": "qwe213312/k25FCdfEOoEJ42S6",
      "source_type": "github_tree_index",
      "status": "unverified",
      "confidence_score": 25
    }
  ]
}
