{
  "depotid": "2014061",
  "updated_at": "2026-05-17T06:24:35Z",
  "manifests": [
    {
      "depotid": "2014061",
      "manifestid": "1736727953127056087",
      "source_repo": "qwe213312/k25FCdfEOoEJ42S6",
      "source_type": "github_tree_index",
      "status": "unverified",
      "confidence_score": 25
    },
    {
      "depotid": "2014061",
      "manifestid": "3554248872654134711",
      "source_repo": "qwe213312/k25FCdfEOoEJ42S6",
      "source_type": "github_tree_index",
      "status": "unverified",
      "confidence_score": 25
    },
    {
      "depotid": "2014061",
      "manifestid": "3890726243259021351",
      "source_repo": "qwe213312/k25FCdfEOoEJ42S6",
      "source_type": "github_tree_index",
      "status": "unverified",
      "confidence_score": 25
    },
    {
      "depotid": "2014061",
      "manifestid": "4246562100353740296",
      "source_repo": "qwe213312/k25FCdfEOoEJ42S6",
      "source_type": "github_tree_index",
      "status": "unverified",
      "confidence_score": 25
    },
    {
      "depotid": "2014061",
      "manifestid": "4535037133578562818",
      "source_repo": "qwe213312/k25FCdfEOoEJ42S6",
      "source_type": "github_tree_index",
      "status": "unverified",
      "confidence_score": 25
    },
    {
      "depotid": "2014061",
      "manifestid": "4611363459893819964",
      "source_repo": "qwe213312/k25FCdfEOoEJ42S6",
      "source_type": "github_tree_index",
      "status": "unverified",
      "confidence_score": 25
    },
    {
      "depotid": "2014061",
      "manifestid": "495527479037876685",
      "source_repo": "qwe213312/k25FCdfEOoEJ42S6",
      "source_type": "github_tree_index",
      "status": "unverified",
      "confidence_score": 25
    },
    {
      "depotid": "2014061",
      "manifestid": "500296318786006862",
      "source_repo": "qwe213312/k25FCdfEOoEJ42S6",
      "source_type": "github_tree_index",
      "status": "unverified",
      "confidence_score": 25
    },
    {
      "depotid": "2014061",
      "manifestid": "5072580385571898524",
      "source_repo": "qwe213312/k25FCdfEOoEJ42S6",
      "source_type": "github_tree_index",
      "status": "unverified",
      "confidence_score": 25
    },
    {
      "depotid": "2014061",
      "manifestid": "5155348062236321741",
      "source_repo": "qwe213312/k25FCdfEOoEJ42S6",
      "source_type": "github_tree_index",
      "status": "unverified",
      "confidence_score": 25
    },
    {
      "depotid": "2014061",
      "manifestid": "6013316233983066561",
      "source_repo": "qwe213312/k25FCdfEOoEJ42S6",
      "source_type": "github_tree_index",
      "status": "unverified",
      "confidence_score": 25
    },
    {
      "depotid": "2014061",
      "manifestid": "6697670278264319358",
      "source_repo": "qwe213312/k25FCdfEOoEJ42S6",
      "source_type": "github_tree_index",
      "status": "unverified",
      "confidence_score": 25
    },
    {
      "depotid": "2014061",
      "manifestid": "7113453024320658708",
      "source_repo": "qwe213312/k25FCdfEOoEJ42S6",
      "source_type": "github_tree_index",
      "status": "unverified",
      "confidence_score": 25
    },
    {
      "depotid": "2014061",
      "manifestid": "7237378559453909141",
      "source_repo": "qwe213312/k25FCdfEOoEJ42S6",
      "source_type": "github_tree_index",
      "status": "unverified",
      "confidence_score": 25
    },
    {
      "depotid": "2014061",
      "manifestid": "7288072283104064066",
      "source_repo": "qwe213312/k25FCdfEOoEJ42S6",
      "source_type": "github_tree_index",
      "status": "unverified",
      "confidence_score": 25
    },
    {
      "depotid": "2014061",
      "manifestid": "7921191546020521707",
      "source_repo": "qwe213312/k25FCdfEOoEJ42S6",
      "source_type": "github_tree_index",
      "status": "unverified",
      "confidence_score": 25
    },
    {
      "depotid": "2014061",
      "manifestid": "8247603325489688082",
      "source_repo": "qwe213312/k25FCdfEOoEJ42S6",
      "source_type": "github_tree_index",
      "status": "unverified",
      "confidence_score": 25
    },
    {
      "depotid": "2014061",
      "manifestid": "8590775182845212189",
      "source_repo": "qwe213312/k25FCdfEOoEJ42S6",
      "source_type": "github_tree_index",
      "status": "unverified",
      "confidence_score": 25
    },
    {
      "depotid": "2014061",
      "manifestid": "8767231696839048012",
      "source_repo": "qwe213312/k25FCdfEOoEJ42S6",
      "source_type": "github_tree_index",
      "status": "unverified",
      "confidence_score": 25
    },
    {
      "depotid": "2014061",
      "manifestid": "929548667993378648",
      "source_repo": "qwe213312/k25FCdfEOoEJ42S6",
      "source_type": "github_tree_index",
      "status": "unverified",
      "confidence_score": 25
    }
  ]
}
