{
  "depotid": "2103131",
  "updated_at": "2026-05-20T06:50:32Z",
  "manifests": [
    {
      "depotid": "2103131",
      "manifestid": "1070107157470295258",
      "source_repo": "mejikuhibiniu1/k25FCdfEOoEJ42S6",
      "source_type": "github_tree_index",
      "status": "unverified",
      "confidence_score": 25
    },
    {
      "depotid": "2103131",
      "manifestid": "1290524749846458170",
      "source_repo": "mejikuhibiniu1/k25FCdfEOoEJ42S6",
      "source_type": "github_tree_index",
      "status": "unverified",
      "confidence_score": 25
    },
    {
      "depotid": "2103131",
      "manifestid": "1394628148293667359",
      "source_repo": "mejikuhibiniu1/k25FCdfEOoEJ42S6",
      "source_type": "github_tree_index",
      "status": "unverified",
      "confidence_score": 25
    },
    {
      "depotid": "2103131",
      "manifestid": "1729137665979409947",
      "source_repo": "mejikuhibiniu1/k25FCdfEOoEJ42S6",
      "source_type": "github_tree_index",
      "status": "unverified",
      "confidence_score": 25
    },
    {
      "depotid": "2103131",
      "manifestid": "1792936945427446093",
      "source_repo": "mejikuhibiniu1/k25FCdfEOoEJ42S6",
      "source_type": "github_tree_index",
      "status": "unverified",
      "confidence_score": 25
    },
    {
      "depotid": "2103131",
      "manifestid": "1800849858322393917",
      "source_repo": "mejikuhibiniu1/k25FCdfEOoEJ42S6",
      "source_type": "github_tree_index",
      "status": "unverified",
      "confidence_score": 25
    },
    {
      "depotid": "2103131",
      "manifestid": "1924810433202075397",
      "source_repo": "mejikuhibiniu1/k25FCdfEOoEJ42S6",
      "source_type": "github_tree_index",
      "status": "unverified",
      "confidence_score": 25
    },
    {
      "depotid": "2103131",
      "manifestid": "231488641112235769",
      "source_repo": "mejikuhibiniu1/k25FCdfEOoEJ42S6",
      "source_type": "github_tree_index",
      "status": "unverified",
      "confidence_score": 25
    },
    {
      "depotid": "2103131",
      "manifestid": "237523099353006646",
      "source_repo": "mejikuhibiniu1/k25FCdfEOoEJ42S6",
      "source_type": "github_tree_index",
      "status": "unverified",
      "confidence_score": 25
    },
    {
      "depotid": "2103131",
      "manifestid": "2810588594475862057",
      "source_repo": "mejikuhibiniu1/k25FCdfEOoEJ42S6",
      "source_type": "github_tree_index",
      "status": "unverified",
      "confidence_score": 25
    },
    {
      "depotid": "2103131",
      "manifestid": "3397665364264645837",
      "source_repo": "mejikuhibiniu1/k25FCdfEOoEJ42S6",
      "source_type": "github_tree_index",
      "status": "unverified",
      "confidence_score": 25
    },
    {
      "depotid": "2103131",
      "manifestid": "3475415168157486090",
      "source_repo": "mejikuhibiniu1/k25FCdfEOoEJ42S6",
      "source_type": "github_tree_index",
      "status": "unverified",
      "confidence_score": 25
    },
    {
      "depotid": "2103131",
      "manifestid": "3746605676790263491",
      "source_repo": "mejikuhibiniu1/k25FCdfEOoEJ42S6",
      "source_type": "github_tree_index",
      "status": "unverified",
      "confidence_score": 25
    },
    {
      "depotid": "2103131",
      "manifestid": "3847250937096954310",
      "source_repo": "mejikuhibiniu1/k25FCdfEOoEJ42S6",
      "source_type": "github_tree_index",
      "status": "unverified",
      "confidence_score": 25
    },
    {
      "depotid": "2103131",
      "manifestid": "401648576654300403",
      "source_repo": "mejikuhibiniu1/k25FCdfEOoEJ42S6",
      "source_type": "github_tree_index",
      "status": "unverified",
      "confidence_score": 25
    },
    {
      "depotid": "2103131",
      "manifestid": "4017699780447682827",
      "source_repo": "mejikuhibiniu1/k25FCdfEOoEJ42S6",
      "source_type": "github_tree_index",
      "status": "unverified",
      "confidence_score": 25
    },
    {
      "depotid": "2103131",
      "manifestid": "4297765404121393402",
      "source_repo": "mejikuhibiniu1/k25FCdfEOoEJ42S6",
      "source_type": "github_tree_index",
      "status": "unverified",
      "confidence_score": 25
    },
    {
      "depotid": "2103131",
      "manifestid": "4495043951644005785",
      "source_repo": "mejikuhibiniu1/k25FCdfEOoEJ42S6",
      "source_type": "github_tree_index",
      "status": "unverified",
      "confidence_score": 25
    },
    {
      "depotid": "2103131",
      "manifestid": "4524588254858177690",
      "source_repo": "mejikuhibiniu1/k25FCdfEOoEJ42S6",
      "source_type": "github_tree_index",
      "status": "unverified",
      "confidence_score": 25
    },
    {
      "depotid": "2103131",
      "manifestid": "4651435553252806260",
      "source_repo": "mejikuhibiniu1/k25FCdfEOoEJ42S6",
      "source_type": "github_tree_index",
      "status": "unverified",
      "confidence_score": 25
    },
    {
      "depotid": "2103131",
      "manifestid": "4730163643357643168",
      "source_repo": "mejikuhibiniu1/k25FCdfEOoEJ42S6",
      "source_type": "github_tree_index",
      "status": "unverified",
      "confidence_score": 25
    },
    {
      "depotid": "2103131",
      "manifestid": "4777280676791403427",
      "source_repo": "mejikuhibiniu1/k25FCdfEOoEJ42S6",
      "source_type": "github_tree_index",
      "status": "unverified",
      "confidence_score": 25
    },
    {
      "depotid": "2103131",
      "manifestid": "4945920204009270800",
      "source_repo": "mejikuhibiniu1/k25FCdfEOoEJ42S6",
      "source_type": "github_tree_index",
      "status": "unverified",
      "confidence_score": 25
    },
    {
      "depotid": "2103131",
      "manifestid": "5022261199346388406",
      "source_repo": "mejikuhibiniu1/k25FCdfEOoEJ42S6",
      "source_type": "github_tree_index",
      "status": "unverified",
      "confidence_score": 25
    },
    {
      "depotid": "2103131",
      "manifestid": "5025500767243135517",
      "source_repo": "mejikuhibiniu1/k25FCdfEOoEJ42S6",
      "source_type": "github_tree_index",
      "status": "unverified",
      "confidence_score": 25
    },
    {
      "depotid": "2103131",
      "manifestid": "509980007774567514",
      "source_repo": "mejikuhibiniu1/k25FCdfEOoEJ42S6",
      "source_type": "github_tree_index",
      "status": "unverified",
      "confidence_score": 25
    },
    {
      "depotid": "2103131",
      "manifestid": "5173760054945086463",
      "source_repo": "mejikuhibiniu1/k25FCdfEOoEJ42S6",
      "source_type": "github_tree_index",
      "status": "unverified",
      "confidence_score": 25
    },
    {
      "depotid": "2103131",
      "manifestid": "5230375853996786478",
      "source_repo": "mejikuhibiniu1/k25FCdfEOoEJ42S6",
      "source_type": "github_tree_index",
      "status": "unverified",
      "confidence_score": 25
    },
    {
      "depotid": "2103131",
      "manifestid": "5238713578903775841",
      "source_repo": "mejikuhibiniu1/k25FCdfEOoEJ42S6",
      "source_type": "github_tree_index",
      "status": "unverified",
      "confidence_score": 25
    },
    {
      "depotid": "2103131",
      "manifestid": "5278086105938173849",
      "source_repo": "mejikuhibiniu1/k25FCdfEOoEJ42S6",
      "source_type": "github_tree_index",
      "status": "unverified",
      "confidence_score": 25
    },
    {
      "depotid": "2103131",
      "manifestid": "5587283403572167243",
      "source_repo": "mejikuhibiniu1/k25FCdfEOoEJ42S6",
      "source_type": "github_tree_index",
      "status": "unverified",
      "confidence_score": 25
    },
    {
      "depotid": "2103131",
      "manifestid": "5788472203083716717",
      "source_repo": "mejikuhibiniu1/k25FCdfEOoEJ42S6",
      "source_type": "github_tree_index",
      "status": "unverified",
      "confidence_score": 25
    },
    {
      "depotid": "2103131",
      "manifestid": "5901531626664629262",
      "source_repo": "mejikuhibiniu1/k25FCdfEOoEJ42S6",
      "source_type": "github_tree_index",
      "status": "unverified",
      "confidence_score": 25
    },
    {
      "depotid": "2103131",
      "manifestid": "634142701285133388",
      "source_repo": "mejikuhibiniu1/k25FCdfEOoEJ42S6",
      "source_type": "github_tree_index",
      "status": "unverified",
      "confidence_score": 25
    },
    {
      "depotid": "2103131",
      "manifestid": "6788864574899848199",
      "source_repo": "mejikuhibiniu1/k25FCdfEOoEJ42S6",
      "source_type": "github_tree_index",
      "status": "unverified",
      "confidence_score": 25
    },
    {
      "depotid": "2103131",
      "manifestid": "6879268420074552713",
      "source_repo": "mejikuhibiniu1/k25FCdfEOoEJ42S6",
      "source_type": "github_tree_index",
      "status": "unverified",
      "confidence_score": 25
    },
    {
      "depotid": "2103131",
      "manifestid": "733261806432878288",
      "source_repo": "mejikuhibiniu1/k25FCdfEOoEJ42S6",
      "source_type": "github_tree_index",
      "status": "unverified",
      "confidence_score": 25
    },
    {
      "depotid": "2103131",
      "manifestid": "733386061542994565",
      "source_repo": "mejikuhibiniu1/k25FCdfEOoEJ42S6",
      "source_type": "github_tree_index",
      "status": "unverified",
      "confidence_score": 25
    },
    {
      "depotid": "2103131",
      "manifestid": "7724764798287606345",
      "source_repo": "mejikuhibiniu1/k25FCdfEOoEJ42S6",
      "source_type": "github_tree_index",
      "status": "unverified",
      "confidence_score": 25
    },
    {
      "depotid": "2103131",
      "manifestid": "7811489659927163739",
      "source_repo": "mejikuhibiniu1/k25FCdfEOoEJ42S6",
      "source_type": "github_tree_index",
      "status": "unverified",
      "confidence_score": 25
    },
    {
      "depotid": "2103131",
      "manifestid": "798753420184566964",
      "source_repo": "mejikuhibiniu1/k25FCdfEOoEJ42S6",
      "source_type": "github_tree_index",
      "status": "unverified",
      "confidence_score": 25
    },
    {
      "depotid": "2103131",
      "manifestid": "8136086391639453840",
      "source_repo": "mejikuhibiniu1/k25FCdfEOoEJ42S6",
      "source_type": "github_tree_index",
      "status": "unverified",
      "confidence_score": 25
    },
    {
      "depotid": "2103131",
      "manifestid": "8187683453723081834",
      "source_repo": "mejikuhibiniu1/k25FCdfEOoEJ42S6",
      "source_type": "github_tree_index",
      "status": "unverified",
      "confidence_score": 25
    },
    {
      "depotid": "2103131",
      "manifestid": "8232844342858419326",
      "source_repo": "mejikuhibiniu1/k25FCdfEOoEJ42S6",
      "source_type": "github_tree_index",
      "status": "unverified",
      "confidence_score": 25
    },
    {
      "depotid": "2103131",
      "manifestid": "8259162787899434320",
      "source_repo": "mejikuhibiniu1/k25FCdfEOoEJ42S6",
      "source_type": "github_tree_index",
      "status": "unverified",
      "confidence_score": 25
    },
    {
      "depotid": "2103131",
      "manifestid": "8455027429937872581",
      "source_repo": "mejikuhibiniu1/k25FCdfEOoEJ42S6",
      "source_type": "github_tree_index",
      "status": "unverified",
      "confidence_score": 25
    },
    {
      "depotid": "2103131",
      "manifestid": "8494844599770481445",
      "source_repo": "mejikuhibiniu1/k25FCdfEOoEJ42S6",
      "source_type": "github_tree_index",
      "status": "unverified",
      "confidence_score": 25
    },
    {
      "depotid": "2103131",
      "manifestid": "8556939495206669845",
      "source_repo": "mejikuhibiniu1/k25FCdfEOoEJ42S6",
      "source_type": "github_tree_index",
      "status": "unverified",
      "confidence_score": 25
    }
  ]
}
