{
  "depotid": "582401",
  "updated_at": "2026-05-16T05:56:11Z",
  "manifests": [
    {
      "depotid": "582401",
      "manifestid": "431513253832636808",
      "source_repo": "Sainan/k25FCdfEOoEJ42S6",
      "source_type": "github_tree_index",
      "status": "unverified",
      "confidence_score": 25
    },
    {
      "depotid": "582401",
      "manifestid": "6942055620073268713",
      "source_repo": "Sainan/k25FCdfEOoEJ42S6",
      "source_type": "github_tree_index",
      "status": "unverified",
      "confidence_score": 25
    }
  ]
}
